CHANGELOG.txt
LICENCE.txt
MANIFEST.in
README.txt
setup.py
jabutixlib/__init__.py
jabutixlib.egg-info/PKG-INFO
jabutixlib.egg-info/SOURCES.txt
jabutixlib.egg-info/dependency_links.txt
jabutixlib.egg-info/requires.txt
jabutixlib.egg-info/top_level.txt