Metadata-Version: 1.1
Name: jabutixlib
Version: 0.0.1
Summary: A library to interacting with a simple educational device called the jabuti
Home-page: UNKNOWN
Author: Davi Feliciano Nonnenmacher
Author-email: davifn1@gmail.com
License: MIT
Keywords: education
Platform: UNKNOWN
Classifier: Development Status :: 5 - Production/Stable
Classifier: Intended Audience :: Education
Classifier: Operating System :: Microsoft :: Windows :: Windows 10
Classifier: License :: OSI Approved :: MIT License
Classifier: Programming Language :: Python :: 3
